<templateSet group="bukkit">
  <template name="EventHandler" value="@org.bukkit.event.EventHandler&#10;void $name$($EVENT$ event){&#10;   $statement$&#10;}" shortcut="ENTER" description="" toReformat="true" toShortenFQNames="true" useStaticImport="true">
    <variable name="name" expression="" defaultValue="" alwaysStopAt="true" />
    <variable name="EVENT" expression="" defaultValue="" alwaysStopAt="true" />
    <variable name="statement" expression="" defaultValue="event" alwaysStopAt="true" />
    <context>
      <option name="JAVA_DECLARATION" value="true" />
    </context>
  </template>
</templateSet>